dascutils/__init__.py
dascutils/io.py
dascutils/plots.py
dascutils-1.3.0.data/scripts/DownloadDASC.py
dascutils-1.3.0.data/scripts/PlotDASC.py
dascutils-1.3.0.dist-info/DESCRIPTION.rst
dascutils-1.3.0.dist-info/METADATA
dascutils-1.3.0.dist-info/RECORD
dascutils-1.3.0.dist-info/WHEEL
dascutils-1.3.0.dist-info/metadata.json
dascutils-1.3.0.dist-info/top_level.txt
