Metadata-Version: 2.0
Name: dascutils
Version: 1.3.0
Summary: Utilities for UAF Digital All-Sky Camera: reading and plotting
Home-page: https://github.com/scivision/dascutils
Author: Michael Hirsch, Ph.D.
Author-email: UNKNOWN
License: UNKNOWN
Platform: UNKNOWN
Classifier: Development Status :: 4 - Beta
Classifier: Environment :: Console
Classifier: Intended Audience :: Science/Research
Classifier: Operating System :: OS Independent
Classifier: Programming Language :: Python :: 3.6
Classifier: Programming Language :: Python :: 3.7
Classifier: Topic :: Scientific/Engineering :: Atmospheric Science
Requires-Python: >=3.6
Requires-Dist: python-dateutil
Requires-Dist: numpy (>=1.13)
Requires-Dist: astropy
Requires-Dist: xarray
Requires-Dist: scikit-image
Requires-Dist: scipy
Provides-Extra: io
Requires-Dist: themisasi; extra == 'io'
Provides-Extra: plots
Requires-Dist: matplotlib; extra == 'plots'
Requires-Dist: scipy; extra == 'plots'
Provides-Extra: tests
Requires-Dist: pytest; extra == 'tests'
Requires-Dist: nose; extra == 'tests'
Requires-Dist: coveralls; extra == 'tests'
